embedder/__init__.py
embedder/core.py
embedder-0.0.7.dist-info/METADATA
embedder-0.0.7.dist-info/WHEEL
embedder-0.0.7.dist-info/top_level.txt
embedder-0.0.7.dist-info/RECORD
