Metadata-Version: 2.1
Name: embedder
Version: 0.0.7
Summary: UNKNOWN
Home-page: UNKNOWN
Author: UNKNOWN
Author-email: UNKNOWN
License: UNKNOWN
Platform: UNKNOWN
Requires-Dist: base-processor (==0.0.2)
Requires-Dist: sklearn
Requires-Dist: pandas
Requires-Dist: numpy
Requires-Dist: spacy
Requires-Dist: feather-format
